setup.py
menoo/__init__.py
menoo.egg-info/PKG-INFO
menoo.egg-info/SOURCES.txt
menoo.egg-info/dependency_links.txt
menoo.egg-info/requires.txt
menoo.egg-info/top_level.txt