Metadata-Version: 1.1
Name: menoo
Version: 0.0.2
Summary: a simple, deploy ready interactive cli menu
Home-page: https://www.github.com/illberoy/menoo
Author: Roy Sommer
Author-email: UNKNOWN
License: UNKNOWN
Download-URL: https://github.com/illberoy/menoo/tarball/0.0.2
Platform: UNKNOWN
